README.rst
setup.py
odoo_upgrade/__init__.py
odoo_upgrade/__main__.py
odoo_upgrade/odoo_upgrade.py
odoo_upgrade/version.py
odoo_upgrade.egg-info/PKG-INFO
odoo_upgrade.egg-info/SOURCES.txt
odoo_upgrade.egg-info/dependency_links.txt
odoo_upgrade.egg-info/entry_points.txt
odoo_upgrade.egg-info/requires.txt
odoo_upgrade.egg-info/top_level.txt