Metadata-Version: 1.1
Name: odoo-upgrade
Version: 1.3
Summary: Command line tool to upgrade your Odoo database
Home-page: https://github.com/olilau/odoo-upgrade
Author: olivier Laurent
Author-email: olilau@gmail.com
License: GPLv2
Keywords: odoo openerp database upgrade
Platform: UNKNOWN
Classifier: Development Status :: 5 - Production/Stable
Classifier: Intended Audience :: Information Technology
Classifier: License :: OSI Approved :: GNU General Public License v2 (GPLv2)
Classifier: Environment :: Console
Classifier: Topic :: Database
Classifier: Programming Language :: Python :: 2.7
Classifier: Operating System :: POSIX
